adaptgym/__init__.py
adaptgym/envs/__init__.py
adaptgym/envs/cdmc/__init__.py
adaptgym/envs/cdmc/rl/__init__.py
adaptgym/envs/cdmc/rl/control.py
adaptgym/envs/cdmc/suite/__init__.py
adaptgym/envs/cdmc/suite/acrobot.py
adaptgym/envs/cdmc/suite/acrobot.xml
adaptgym/envs/cdmc/suite/acrobot_c.xml
adaptgym/envs/cdmc/suite/ball_in_cup.py
adaptgym/envs/cdmc/suite/ball_in_cup.xml
adaptgym/envs/cdmc/suite/ball_in_cup_c.xml
adaptgym/envs/cdmc/suite/cartpole.py
adaptgym/envs/cdmc/suite/cartpole.xml
adaptgym/envs/cdmc/suite/cartpole_c.xml
adaptgym/envs/cdmc/suite/cheetah.py
adaptgym/envs/cdmc/suite/cheetah.xml
adaptgym/envs/cdmc/suite/cheetah_c.xml
adaptgym/envs/cdmc/suite/common/__init__.py
adaptgym/envs/cdmc/suite/common/materials.xml
adaptgym/envs/cdmc/suite/common/skybox.xml
adaptgym/envs/cdmc/suite/common/visual.xml
adaptgym/envs/cdmc/suite/quadruped.py
adaptgym/envs/cdmc/suite/quadruped.xml
adaptgym/envs/crafter/__init__.py
adaptgym/envs/crafter/common.py
adaptgym/envs/crafter/plot_counts.py
adaptgym/envs/crafter/plot_reward.py
adaptgym/envs/crafter/plot_scores.py
adaptgym/envs/crafter/plot_spectrum.py
adaptgym/envs/crafter/read_metrics.py
adaptgym/envs/distracting_control/__init__.py
adaptgym/envs/distracting_control/background.py
adaptgym/envs/distracting_control/camera.py
adaptgym/envs/distracting_control/camera_t3st.py
adaptgym/envs/distracting_control/color.py
adaptgym/envs/distracting_control/data/__init__.py
adaptgym/envs/distracting_control/data/bmx-bumps/00000.jpg
adaptgym/envs/distracting_control/data/bmx-bumps/00001.jpg
adaptgym/envs/distracting_control/data/bmx-bumps/00002.jpg
adaptgym/envs/distracting_control/data/bmx-bumps/00003.jpg
adaptgym/envs/distracting_control/data/bmx-bumps/00004.jpg
adaptgym/envs/distracting_control/data/bmx-bumps/00005.jpg
adaptgym/envs/distracting_control/data/bmx-bumps/00006.jpg
adaptgym/envs/distracting_control/data/bmx-bumps/00007.jpg
adaptgym/envs/distracting_control/data/bmx-bumps/00008.jpg
adaptgym-0.1.2.dist-info/LICENSE
adaptgym-0.1.2.dist-info/WHEEL
adaptgym-0.1.2.dist-info/METADATA
adaptgym-0.1.2.dist-info/RECORD
